{"cameraMode":{"drawMode":0,"name":"Shaded","section":"Shading Mode"},"sceneLighting":false,"audioPlay":false,"sceneViewState":{"m_AlwaysRefresh":false,"showFog":true,"showSkybox":false,"showFlares":true,"showImageEffects":true,"showParticleSystems":true,"showVisualEffectGraphs":true,"m_FxEnabled":true},"in2DMode":false,"pivot":{"x":-9.28815746307373,"y":-18.999038696289064,"z":0.9245800971984863},"rotation":{"x":-0.38173404335975649,"y":0.5772550702095032,"z":-0.34862685203552248,"w":-0.6320784687995911},"size":0.8660253882408142,"orthographic":false}